setup.py
codebottle/__init__.py
codebottle.egg-info/PKG-INFO
codebottle.egg-info/SOURCES.txt
codebottle.egg-info/dependency_links.txt
codebottle.egg-info/not-zip-safe
codebottle.egg-info/requires.txt
codebottle.egg-info/top_level.txt