Metadata-Version: 1.0
Name: codebottle
Version: 0.0.1
Summary: A Python library to interact with CodeBottle's API
Home-page: https://github.com/codebottle-io/codebottle-python
Author: Luke J.
Author-email: support@codebottle.io
License: GNU
Platform: UNKNOWN
